setup.py
traceurl/__init__.py
traceurl.egg-info/PKG-INFO
traceurl.egg-info/SOURCES.txt
traceurl.egg-info/dependency_links.txt
traceurl.egg-info/requires.txt
traceurl.egg-info/top_level.txt