Metadata-Version: 1.0
Name: traceurl
Version: 0.9.1
Summary: Python Url Tracing Library
Home-page: https://github.com/charsyam/traceurl
Author: DaeMyung Kang
Author-email: charsyam@gmail.com
License: UNKNOWN
Platform: any
